{"town":{"retired":[{"TYPE":"player","DESCRIPTION":"","LEFT":0,"RIGHT":0,"INVENTORY":[{"type":"weapon","subclass":"axe","description":"","effect":"","runes":[{"value":70,"type":"rune","target":"weapon","name":"Powerful","description":"+20% Weapon Base Damage on Attacks","equipped":false},{"value":70,"type":"rune","target":"weapon","name":"Accurate","description":"Re-Roll missed attacks.","equipped":false}],"name":"Great Axe","hands":2,"value":70,"attacks":[0,1],"chance":60,"min":4,"max":52,"pen":40,"AP":12,"range":1,"equipped":true,"canDrop":true},{"name":"Stamina Potion","type":"potion","value":10,"equipped":false,"runes":[],"description":"Restores ~50 Stamina"}],"SKILLS":[],"ABILITIES":[],"SPELLS":[],"NAME":"Goliath","ID":"462829989465948180Goliathpeasant87263","CLASS":"peasant","STATS":[2,0,2,4,2,0],"SP":0,"HP":40,"MANA":0,"GOLD":71,"STAMINA":60,"AP":12,"ENDED":false,"LEVEL":3,"XP":216,"ARMOR":[0,0],"LOCATION":"The Wilted Woods","BUILDING":"guild hall","BACKPACK":false,"EFFECTS":[],"ROW":4,"ATTACKS":0,"CASTS":0,"TRADING":"","HITS":[5,5],"ATTEMPTS":[7,7]},{"TYPE":"player","DESCRIPTION":"","LEFT":0,"RIGHT":1,"INVENTORY":[{"type":"weapon","subclass":"blade","description":"","effect":"","runes":[{"value":70,"type":"rune","target":"weapon","name":"Precise","description":"+2 Damage per Attack","equipped":false},{"value":75,"type":"rune","target":"weapon","name":"Leeching","description":"Heal +2 HP per attack.","equipped":false},{"value":70,"type":"rune","target":"weapon","name":"Gamble","description":"-1 Damage. +4 Max Damage.","equipped":false}],"name":"Dagger","hands":1,"value":15,"attacks":[3,3],"chance":70,"min":2,"max":9,"pen":0,"AP":1,"range":1,"equipped":true},{"type":"weapon","subclass":"blade","description":"","effect":"","runes":[{"value":70,"type":"rune","target":"weapon","name":"Gamble","description":"-1 Damage. +4 Max Damage.","equipped":false},{"value":70,"type":"rune","target":"weapon","name":"Precise","description":"+2 Damage per Attack","equipped":false},{"value":75,"type":"rune","target":"weapon","name":"Siphoning","description":"Gain +5 Stamina per attack.","equipped":false}],"name":"Dagger","hands":1,"value":15,"attacks":[3,3],"chance":70,"min":2,"max":9,"pen":0,"AP":1,"range":1,"equipped":true},{"type":"armor","effect":"","name":"Amethyst Tunic","armor":[4,10],"AP":3,"value":75,"runes":[{"value":70,"type":"rune","target":"armor","name":"Reflex","description":"Gain +20% Dodge Chance against physical and magical attacks.","equipped":false},{"value":115,"type":"rune","target":"armor","name":"Tempered","description":"Gain +2 Physical and Magical Armor","equipped":false},{"value":100,"type":"rune","target":"armor","name":"Longevity","description":"Gain +20 Max HP.","equipped":false}],"equipped":true,"description":"An brilliant piece of apparel made of shining, fibrous amethyst."},{"name":"Health Potion","type":"potion","value":15,"equipped":false,"runes":[],"description":"Restores ~25 HP"},{"name":"Health Potion","type":"potion","value":15,"equipped":false,"runes":[],"description":"Restores ~25 HP"},{"name":"Health Potion","type":"potion","value":15,"equipped":false,"runes":[],"description":"Restores ~25 HP"},{"name":"Stamina Potion","type":"potion","value":10,"equipped":false,"runes":[],"description":"Restores ~50 Stamina"}],"SKILLS":[],"ABILITIES":[],"SPELLS":[],"NAME":"Fargus","ID":"462829989465948180Fargusrogue97180","CLASS":"rogue","STATS":[3,0,1,3,2,2],"SP":0,"HP":70,"MANA":0,"GOLD":90,"STAMINA":30,"AP":9,"ENDED":false,"LEVEL":6,"XP":171,"ARMOR":[4,10],"LOCATION":"The Wilted Woods","BUILDING":"guild hall","BACKPACK":true,"EFFECTS":[],"ROW":4,"ATTACKS":0,"CASTS":0,"TRADING":"","HITS":[40,49],"ATTEMPTS":[58,61]}],"prosperity":3059,"quest":{"enemy":"Goblin Archer","numRequired":5,"numKilled":2,"value":115},"graves":[{"NAME":"Kerit","CLASS":"rogue","LEVEL":1},{"NAME":"Cykin","CLASS":"mage","LEVEL":1},{"NAME":"Kira","CLASS":"warrior","LEVEL":1},{"NAME":"Kireta","CLASS":"mage","LEVEL":1},{"NAME":"Help","CLASS":"noble","LEVEL":1},{"NAME":"En","CLASS":"passant","LEVEL":0},{"NAME":"Tira","CLASS":"rogue","LEVEL":1},{"NAME":"Cereih","CLASS":"warrior","LEVEL":1},{"NAME":"Enpassant","CLASS":"peasant","LEVEL":1},{"NAME":"Esmerela","CLASS":"rogue","LEVEL":1},{"NAME":",2","CLASS":"peasant","LEVEL":1},{"NAME":"Hoisin","CLASS":"rogue","LEVEL":2},{"NAME":"Liver","CLASS":"warrior","LEVEL":2},{"NAME":"Peasant","CLASS":"warrior","LEVEL":1},{"NAME":"Waryr","CLASS":"peasant","LEVEL":1},{"NAME":"Peasant","CLASS":"noble","LEVEL":1},{"NAME":"Peasant","CLASS":"noble","LEVEL":1},{"NAME":"Noble","DESCRIPTION":"","CLASS":"peasant","LEVEL":2},{"NAME":"Rogue","DESCRIPTION":"","CLASS":"peasant","LEVEL":1},{"NAME":"Ape","DESCRIPTION":"","CLASS":"rogue","LEVEL":1},{"NAME":"Ape","DESCRIPTION":"","CLASS":"warrior","LEVEL":1},{"NAME":"Ape","DESCRIPTION":"","CLASS":"warrior","LEVEL":1},{"NAME":"Ape","DESCRIPTION":"","CLASS":"ranger","LEVEL":1},{"NAME":"Cekic","DESCRIPTION":"","CLASS":"peasant","LEVEL":1},{"NAME":"Geas","DESCRIPTION":"","CLASS":"peasant","LEVEL":1},{"NAME":"Geas","DESCRIPTION":"","CLASS":"peasant","LEVEL":1},{"NAME":"Salmin","DESCRIPTION":"","CLASS":"noble","LEVEL":1},{"NAME":"Warrior","DESCRIPTION":"","CLASS":"ranger","LEVEL":1},{"NAME":"Geas","DESCRIPTION":"","CLASS":"peasant","LEVEL":1},{"NAME":"Geas","DESCRIPTION":"","CLASS":"peasant","LEVEL":1},{"NAME":"Tobbo","DESCRIPTION":"","CLASS":"warrior","LEVEL":1},{"NAME":"Krogg","DESCRIPTION":"","CLASS":"warrior","LEVEL":1},{"NAME":"Geas","DESCRIPTION":"","CLASS":"peasant","LEVEL":1},{"NAME":"Cein","DESCRIPTION":"","CLASS":"mage","LEVEL":1},{"NAME":"Geas","DESCRIPTION":"","CLASS":"peasant","LEVEL":1},{"NAME":"Geas","DESCRIPTION":"","CLASS":"ranger","LEVEL":1},{"NAME":"Cein","DESCRIPTION":"","CLASS":"mage","LEVEL":1},{"NAME":"Geas","DESCRIPTION":"","CLASS":"peasant","LEVEL":2},{"NAME":"Cein","DESCRIPTION":"","CLASS":"mage","LEVEL":3},{"NAME":"Deya","DESCRIPTION":"","CLASS":"warrior","LEVEL":1},{"NAME":"Yereov","DESCRIPTION":"","CLASS":"noble","LEVEL":1},{"NAME":"Dira","DESCRIPTION":"","CLASS":"noble","LEVEL":1},{"NAME":"Alora","DESCRIPTION":"","CLASS":"noble","LEVEL":1},{"NAME":"Lekov","DESCRIPTION":"","CLASS":"noble","LEVEL":1},{"NAME":"Cesdes","DESCRIPTION":"","CLASS":"noble","LEVEL":1},{"NAME":"Bevinon","DESCRIPTION":"","CLASS":"warrior","LEVEL":1},{"NAME":"Edit","DESCRIPTION":"","CLASS":"warrior","LEVEL":1},{"NAME":"Mara","DESCRIPTION":"","CLASS":"warrior","LEVEL":1},{"NAME":"Yedo","DESCRIPTION":"","CLASS":"noble","LEVEL":1}]},"462829989465948180":{"CATCH":{"fish":{"name":"Freshwater Sunfish","type":"fish","value":15,"equipped":false,"runes":[],"description":"A small, bright fish, yellow and gold like the sunset from which its name is derived."},"date":"2024-04-12T21:33:54.126Z","caught":true,"valid":false,"location":"The Acrid Swamp"},"CHARACTER":{"TYPE":"player","DESCRIPTION":"","LEFT":0,"RIGHT":0,"INVENTORY":[{"type":"weapon","subclass":"blunt","description":"","effect":"","runes":[],"name":"Club","hands":2,"value":15,"attacks":[1,1],"chance":60,"min":12,"max":18,"pen":60,"AP":6,"range":1,"equipped":true,"canDrop":true}],"SKILLS":[],"ABILITIES":[],"SPELLS":[],"NAME":"Vena","ID":"462829989465948180Venapeasant11181","CLASS":"peasant","STATS":[2,0,2,0,0,0],"SP":4,"HP":40,"MANA":0,"GOLD":0,"STAMINA":60,"AP":0,"ENDED":true,"LEVEL":1,"XP":0,"ARMOR":[0,0],"LOCATION":"The Acrid Swamp","BUILDING":"","BACKPACK":false,"EFFECTS":[],"ROW":2,"ATTACKS":0,"CASTS":0,"TRADING":"","HITS":[1,1],"ATTEMPTS":[1,1]}},"388524907450990603":{"CHARACTER":{"TYPE":"player","DESCRIPTION":"","LEFT":2,"RIGHT":2,"INVENTORY":[{"name":"Elemental Spellbook","type":"spellbook","value":50,"equipped":false,"runes":[],"description":"Used to learn strong elemental spells."},{"type":"armor","effect":"","name":"Silk Armor","armor":[3,3],"AP":2,"value":75,"runes":[{"value":100,"type":"rune","target":"armor","name":"Longevity","description":"Gain +20 Max HP.","equipped":false}],"equipped":true,"description":"An exquisite piece of incredibly light armor."},{"name":"Scepter","type":"staff","value":125,"equipped":true,"runes":[{"value":150,"type":"rune","target":"staff","name":"Cinnabar","description":"Whenever you damage a target with a spell, reduce its magic armor by 1.","equipped":false},{"value":100,"type":"rune","target":"staff","name":"Charcoal","description":"Your spells gain +1 Bonus DMG.","equipped":false}],"description":"Used to cast spells. Adds +1 Damage to your spells. Spells have a 10% Chance to not use AP."},{"name":"Imperial Spellbook","type":"spellbook","value":50,"equipped":false,"runes":[],"description":"Used to learn spells that buff your other spells."},{"name":"Blood Spellbook","type":"spellbook","value":50,"equipped":false,"runes":[],"description":"Used to learn powerful spells which cost HP to use."},{"name":"Health Potion","type":"potion","value":15,"equipped":false,"runes":[],"description":"Restores ~25 HP"},{"name":"Stamina Potion","type":"potion","value":10,"equipped":false,"runes":[],"description":"Restores ~50 Stamina"},{"name":"Stamina Potion","type":"potion","value":10,"equipped":false,"runes":[],"description":"Restores ~50 Stamina"},{"name":"Stamina Potion","type":"potion","value":10,"equipped":false,"runes":[],"description":"Restores ~50 Stamina"},{"name":"Stamina Potion","type":"potion","value":10,"equipped":false,"runes":[],"description":"Restores ~50 Stamina"}],"SKILLS":[],"ABILITIES":[],"SPELLS":[{"type":"spell","range":6,"name":"Arcane Strike","description":"Deal 6 Damage to a Target","AP":5,"HP":0,"gold":0,"school":"self-taught"},{"type":"spell","range":6,"name":"Wall of Fire","description":"Deal 3-6 damage to every enemy in a selected row.","AP":6,"HP":0,"gold":0,"school":"elemental"},{"type":"spell","range":6,"name":"Earthen Spear","description":"Deal 8-12 damage to an adjacent target.","AP":7,"HP":0,"gold":0,"school":"elemental"},{"type":"spell","range":6,"name":"Blizzard","description":"Deal 2-4 damage to all enemies. Has a small chance to stun them.","AP":8,"HP":0,"gold":0,"school":"elemental"},{"type":"spell","range":6,"name":"Entangle","description":"Summon vines to a row, dealing 2-4 damage and having a chance to root enemies in place.","AP":6,"HP":0,"gold":0,"school":"elemental"},{"type":"spell","range":6,"name":"Freeze","description":"Deal 2-6 damage to a target and freeze them, stunning them for a turn.","AP":8,"HP":0,"gold":0,"school":"elemental"},{"type":"spell","range":6,"name":"Chain Lightning","description":"Deal 2-6 damage per target to 3 targets.","AP":7,"HP":0,"gold":0,"school":"elemental"},{"type":"spell","range":6,"name":"Restitution","description":"All allies are restored +15 Stamina.","AP":5,"HP":10,"gold":0,"school":"blood"},{"type":"spell","range":6,"name":"Balanced Humors","description":"Gain 5 AP.","AP":0,"HP":5,"gold":0,"school":"blood"}],"NAME":"Shlongus","ID":"388524907450990603Shlongusmage93727","CLASS":"mage","STATS":[2,4,1,0,4,0],"SP":0,"HP":60,"MANA":0,"GOLD":18,"STAMINA":35,"AP":16,"ENDED":false,"LEVEL":6,"XP":20,"ARMOR":[3,3],"LOCATION":"Merchant's Lane","BUILDING":"barbershop","BACKPACK":true,"EFFECTS":[],"ROW":4,"ATTACKS":0,"CASTS":144,"TRADING":"","HITS":[1,1],"ATTEMPTS":[1,1]}},"73526294146449408":{"CHARACTER":{"TYPE":"player","DESCRIPTION":"","LEFT":-1,"RIGHT":3,"INVENTORY":[{"type":"weapon","subclass":"blunt","description":"","effect":"","runes":[{"value":70,"type":"rune","target":"weapon","name":"Maladious","description":"If a target is debuffed, gain +2 Damage, +1 Damage per Debuff.","equipped":false},{"value":70,"type":"rune","target":"weapon","name":"Powerful","description":"+20% Weapon Base Damage on Attacks","equipped":false}],"name":"Club","hands":2,"value":15,"attacks":[0,1],"chance":60,"min":12,"max":18,"pen":60,"AP":6,"range":1,"equipped":false},{"type":"armor","effect":"","name":"Leather Cuirass","armor":[4,0],"AP":2,"value":40,"runes":[],"equipped":true,"description":"A plain leather cuirass, well-worn and scuffed."},{"name":"Health Potion","type":"potion","value":15,"equipped":false,"runes":[],"description":"Restores ~25 HP"},{"type":"weapon","subclass":"shield","description":"","effect":"","runes":[],"name":"Buckler","hands":1,"value":20,"attacks":[0,1],"chance":90,"min":4,"max":6,"pen":50,"AP":4,"range":1,"equipped":true}],"SKILLS":[],"ABILITIES":[],"SPELLS":[],"NAME":"B'ous'g'ous","ID":"73526294146449408B'ous'g'ouspeasant76433","CLASS":"peasant","STATS":[4,0,2,0,4,0],"SP":0,"HP":60,"MANA":0,"GOLD":30,"STAMINA":50,"AP":3,"ENDED":false,"LEVEL":3,"XP":243,"ARMOR":[4,0],"LOCATION":"Merchant's Lane","BUILDING":"barbershop","BACKPACK":false,"EFFECTS":[],"ROW":0,"ATTACKS":0,"CASTS":0,"TRADING":"","HITS":[2,2],"ATTEMPTS":[3,2]}},"522873208588992534":{"CHARACTER":{"TYPE":"player","DESCRIPTION":"","LEFT":0,"RIGHT":0,"INVENTORY":[{"name":"Wand","type":"staff","value":30,"equipped":true,"runes":[],"description":"Used to cast spells."},{"name":"Elemental Spellbook","type":"spellbook","value":50,"equipped":false,"runes":[],"description":"Used to learn strong elemental spells."}],"SKILLS":[],"ABILITIES":[],"SPELLS":[{"type":"spell","range":6,"name":"Arcane Strike","description":"Deal 6 Damage to a Target","AP":5,"HP":0,"gold":0,"school":"self-taught"},{"type":"spell","range":6,"name":"Entangle","description":"Summon vines to a row, dealing 2-4 damage and having a chance to root enemies in place.","AP":6,"HP":0,"gold":0,"school":"elemental"},{"type":"spell","range":6,"name":"Stoneskin","description":"+8 Physical Armor +4 Magical Armor for 3 turns.","AP":6,"HP":0,"gold":0,"school":"elemental"},{"type":"spell","range":6,"name":"Chain Lightning","description":"Deal 2-6 damage per target to 3 targets.","AP":7,"HP":0,"gold":0,"school":"elemental"},{"type":"spell","range":6,"name":"Blizzard","description":"Deal 2-4 damage to all enemies. Has a small chance to stun them.","AP":8,"HP":0,"gold":0,"school":"elemental"},{"type":"spell","range":6,"name":"Gale","description":"Push a row of enemies back one row.","AP":5,"HP":0,"gold":0,"school":"elemental"},{"type":"spell","range":6,"name":"Earthen Spear","description":"Deal 8-12 damage to an adjacent target.","AP":7,"HP":0,"gold":0,"school":"elemental"}],"NAME":"Ducksauce","ID":"522873208588992534Ducksaucemage56835","CLASS":"mage","STATS":[0,3,2,0,1,0],"SP":1,"HP":8,"MANA":0,"GOLD":89,"STAMINA":60,"AP":9,"ENDED":false,"LEVEL":2,"XP":71,"ARMOR":[0,0],"LOCATION":"The Wilted Woods","BUILDING":"","BACKPACK":false,"EFFECTS":[],"ROW":4,"ATTACKS":0,"CASTS":7,"TRADING":"","HITS":[1,1],"ATTEMPTS":[1,1]}},"569277281046888488":{"CHARACTER":null},"428758737398923264":{"CHARACTER":null},"328162295589109761":{"CHARACTER":null},"211316647208812545":{"CHARACTER":{"TYPE":"player","DESCRIPTION":"the decadence of just being Geas","LEFT":2,"RIGHT":1,"INVENTORY":[{"type":"armor","effect":"","name":"Scale Armor","armor":[6,0],"AP":5,"value":50,"runes":[],"equipped":true,"description":"A simple armor made of the overlapping scales of some beast.","canDrop":true},{"type":"weapon","subclass":"shield","description":"","effect":"","runes":[],"name":"Buckler","hands":1,"value":20,"attacks":[0,1],"chance":90,"min":4,"max":6,"pen":50,"AP":4,"range":1,"equipped":true,"canDrop":true},{"type":"weapon","subclass":"blade","description":"","effect":"","runes":[],"name":"Scimitar","hands":1,"value":40,"attacks":[1,2],"chance":75,"min":4,"max":6,"pen":10,"AP":5,"range":1,"equipped":true,"canDrop":true},{"value":60,"type":"rune","target":"weapon","name":"Envenomed","description":"50% Chance to afflict venom on the target.","equipped":false}],"SKILLS":[],"ABILITIES":[],"SPELLS":[],"NAME":"Geas","ID":"211316647208812545Geaspeasant66250","CLASS":"peasant","STATS":[3,0,2,0,3,2],"SP":0,"HP":-5,"MANA":0,"GOLD":8,"STAMINA":11,"AP":1,"ENDED":true,"LEVEL":3,"XP":28,"ARMOR":[6,0],"LOCATION":"The Wilted Woods","BUILDING":"","BACKPACK":false,"EFFECTS":[{"name":"Rooted","type":"debuff","description":"Unable to Move.","duration":0},{"name":"Venom","type":"debuff","description":"Take 4 dmg per turn.","duration":2}],"ROW":0,"ATTACKS":0,"CASTS":0,"TRADING":"","HITS":[6,4],"ATTEMPTS":[8,4]}}}